PyTabFy/__init__.py
PyTabFy/Dummy/__init__.py
PyTabFy/Dummy/dummy.py
PyTabFy/Examples/__init__.py
PyTabFy/Examples/examples.py
PyTabFy/Examples/interactive_example.py
PyTabFy/Others/__init__.py
PyTabFy/Others/version.py
PyTabFy/PyTConfigs/__init__.py
PyTabFy/PyTConfigs/global_configs.py
PyTabFy/PyTConfigs/table_configs.py
PyTabFy/PyTCore/__init__.py
PyTabFy/PyTCore/Exceptions/__init__.py
PyTabFy/PyTCore/Exceptions/exceptions.py
PyTabFy/PyTCore/Tables/__init__.py
PyTabFy/PyTCore/Tables/Core/__init__.py
PyTabFy/PyTCore/Tables/Core/base_table.py
PyTabFy/PyTCore/Tables/Core/table_builder.py
PyTabFy/PyTCore/Tables/Core/table_logger.py
PyTabFy/PyTCore/Tables/Core/table_printer.py
PyTabFy/PyTCore/Tables/Default/center_aligned_table.py
PyTabFy/PyTCore/Tables/Default/default_table.py
PyTabFy/PyTCore/Tables/Default/left_aligned_table.py
PyTabFy/PyTCore/Tables/Default/right_aligned_table.py
PyTabFy/PyTCore/Types/__init__.py
PyTabFy/PyTCore/Types/custom_types.py
PyTabFy/PyTCore/Warnings/__init__.py
PyTabFy/PyTCore/Warnings/warnings.py
PyTabFy/PyTEnums/__init__.py
PyTabFy/PyTEnums/enums.py
PyTabFy/PyTUtils/__init__.py
PyTabFy/PyTUtils/inputs.py
PyTabFy/PyTUtils/strings.py
PyTabFy/PyTUtils/utils.py
PyTabFy/PyTUtils/validation.py
pytabfy-1.0.1.dist-info/licenses/LICENSE
pytabfy-1.0.1.dist-info/METADATA
pytabfy-1.0.1.dist-info/WHEEL
pytabfy-1.0.1.dist-info/top_level.txt
pytabfy-1.0.1.dist-info/RECORD
