Metadata-Version: 2.4
Name: PyTabFy
Version: 1.0.1
Summary: Builds and Displays Customizable Tables
Author-email: Fabrício dos Santos Moreira <dev.fabriciodossantosmoreira@gmail.com>
Project-URL: repository, https://github.com/FabricioDosSantosMoreira/PyTabFy
Keywords: Python,Library,Tables,Customizable,ASCII,Non-ASCII
Classifier: Topic :: Software Development :: Libraries :: Python Modules
Classifier: Topic :: Software Development :: User Interfaces
Classifier: Topic :: Utilities
Classifier: Development Status :: 2 - Pre-Alpha
Classifier: License :: OSI Approved :: MIT License
Classifier: Programming Language :: Python
Classifier: Programming Language :: Python :: 3.8
Classifier: Programming Language :: Python :: 3.9
Classifier: Programming Language :: Python :: 3.10
Classifier: Programming Language :: Python :: 3.11
Classifier: Programming Language :: Python :: 3.12
Classifier: Operating System :: OS Independent
Classifier: Environment :: Console
Classifier: Intended Audience :: Developers
Requires-Python: >=3.8
License-File: LICENSE
Requires-Dist: wcwidth
Provides-Extra: dev
Requires-Dist: pytest; extra == "dev"
Requires-Dist: pytest-cov; extra == "dev"
Dynamic: license-file
